[
  {
    "id": "51-la",
    "name": "51.la",
    "builtwith": true
  },
  {
    "id": "960-gs",
    "name": "960.gs",
    "builtwith": true
  },
  {
    "id": "ac-quicktime",
    "name": "AC Quicktime",
    "builtwith": true
  },
  {
    "name": "Accelerated Mobile Pages",
    "builtwith": true,
    "alias": "amp"
  },
  {
    "name": "Add to Any",
    "builtwith": true,
    "alias": "addtoany"
  },
  {
    "id": "addthis",
    "name": "AddThis",
    "builtwith": true,
    "wappalyzer": true
  },
  {
    "id": "addtoany",
    "name": "AddToAny",
    "wappalyzer": true
  },
  {
    "id": "addtocalendar",
    "name": "AddToCalendar",
    "builtwith": true
  },
  {
    "id": "adobe-active-content",
    "name": "Adobe Active Content",
    "builtwith": true
  },
  {
    "id": "adobe-analytics",
    "name": "Adobe Analytics",
    "builtwith": true,
    "wappalyzer": true
  },
  {
    "id": "adobe-coldfusion",
    "name": "Adobe ColdFusion",
    "builtwith": true
  },
  {
    "id": "adobe-cq",
    "name": "Adobe CQ",
    "builtwith": true
  },
  {
    "id": "adobe-cross-domain-configuration",
    "name": "Adobe Cross Domain Configuration",
    "builtwith": true
  },
  {
    "name": "Adobe Dreamweaver",
    "builtwith": true,
    "alias": "dreamweaver"
  },
  {
    "id": "adobe-dtm",
    "name": "Adobe DTM",
    "wappalyzer": true
  },
  {
    "id": "adobe-experience-manager",
    "name": "Adobe Experience Manager",
    "builtwith": true,
    "wappalyzer": true
  },
  {
    "id": "flash",
    "name": "Adobe Flash"
  },
  {
    "id": "adobe-golive",
    "name": "Adobe GoLive",
    "builtwith": true,
    "wappalyzer": true
  },
  {
    "id": "adobe-pagemill",
    "name": "Adobe PageMill",
    "builtwith": true
  },
  {
    "id": "adobe-spry",
    "name": "Adobe Spry",
    "builtwith": true
  },
  {
    "id": "adroll",
    "name": "AdRoll",
    "builtwith": true,
    "wappalyzer": true
  },
  {
    "id": "ajax-libraries-api",
    "name": "AJAX Libraries API",
    "builtwith": true
  },
  {
    "id": "akamai",
    "name": "Akamai",
    "builtwith": true
  },
  {
    "id": "all-in-one-seo-pack",
    "name": "All in One SEO Pack",
    "builtwith": true
  },
  {
    "id": "alternate-protocol",
    "name": "Alternate Protocol",
    "builtwith": true
  },
  {
    "id": "s3",
    "name": "Amazon S3",
    "builtwith": true
  },
  {
    "id": "amp",
    "name": "AMP",
    "wappalyzer": true
  },
  {
    "id": "angular-js",
    "name": "Angular JS",
    "builtwith": true,
    "category": "JavaScript library"
  },
  {
    "id": "angularjs",
    "name": "AngularJS",
    "wappalyzer": true
  },
  {
    "id": "animate-css",
    "name": "animate.css",
    "wappalyzer": true,
    "category": "css"
  },
  {
    "id": "anythingslider",
    "name": "AnythingSlider",
    "builtwith": true
  },
  {
    "id": "apache",
    "name": "Apache",
    "builtwith": true,
    "category": "servers"
  },
  {
    "name": "Apache 1.3",
    "builtwith": true,
    "alias": "apache",
    "category": "servers"
  },
  {
    "name": "Apache 2.0",
    "builtwith": true,
    "alias": "apache",
    "category": "servers"
  },
  {
    "name": "Apache 2.2",
    "builtwith": true,
    "alias": "apache",
    "category": "servers"
  },
  {
    "name": "Apache 2.4",
    "builtwith": true,
    "alias": "apache",
    "category": "servers"
  },
  {
    "id": "apache-tomcat",
    "name": "Apache Tomcat"
  },
  {
    "name": "Apache Tomcat Coyote",
    "builtwith": true,
    "alias": "apache-tomcat",
    "category": "servers"
  },
  {
    "name": "Apache Tomcat JK",
    "builtwith": true,
    "alias": "apache-tomcat",
    "category": "servers"
  },
  {
    "id": "appdynamics",
    "name": "AppDynamics",
    "builtwith": true,
    "wappalyzer": true
  },
  {
    "id": "apple-mobile-web",
    "name": "Apple Mobile Web"
  },
  {
    "name": "Apple Mobile Web App Capable",
    "builtwith": true,
    "alias": "apple-mobile-web"
  },
  {
    "name": "Apple Mobile Web App Status Bar Style",
    "builtwith": true,
    "alias": "apple-mobile-web"
  },
  {
    "name": "Apple Mobile Web Clips Icon",
    "builtwith": true,
    "alias": "apple-mobile-web",
    "category": "icons"
  },
  {
    "name": "Applet",
    "builtwith": true,
    "alias": "java"
  },
  {
    "id": "application-request-routing",
    "name": "Application Request Routing",
    "builtwith": true
  },
  {
    "id": "applyweb",
    "name": "ApplyWeb",
    "builtwith": true
  },
  {
    "id": "appnexus",
    "name": "AppNexus",
    "builtwith": true,
    "wappalyzer": true
  },
  {
    "id": "appnexus-segment-pixel",
    "name": "AppNexus Segment Pixel",
    "builtwith": true
  },
  {
    "id": "arcgis",
    "name": "ArcGIS",
    "builtwith": true
  },
  {
    "name": "ASP.NET",
    "builtwith": true,
    "alias": "microsoft-asp-net"
  },
  {
    "name": "ASP.NET Ajax",
    "builtwith": true,
    "alias": "microsoft-asp-net"
  },
  {
    "name": "ASP.NET MVC",
    "builtwith": true,
    "alias": "microsoft-asp-net"
  },
  {
    "id": "atg-click-to-call",
    "name": "ATG Click to Call",
    "builtwith": true
  },
  {
    "id": "atlassian-jira-issue-collector",
    "name": "Atlassian JIRA Issue Collector",
    "builtwith": true,
    "wappalyzer": true
  },
  {
    "id": "atom",
    "name": "Atom",
    "builtwith": true
  },
  {
    "id": "atomz",
    "name": "Atomz",
    "builtwith": true
  },
  {
    "id": "auth-passthrough",
    "name": "Auth Passthrough",
    "builtwith": true
  },
  {
    "id": "autoptimize",
    "name": "Autoptimize",
    "builtwith": true
  },
  {
    "id": "awstats",
    "name": "AWStats",
    "builtwith": true
  },
  {
    "id": "axios",
    "name": "Axios",
    "builtwith": true
  },
  {
    "name": "Azure Edge",
    "builtwith": true,
    "alias": "microsoft-azure"
  },
  {
    "id": "babel",
    "name": "Babel",
    "wappalyzer": true
  },
  {
    "id": "backbone-js",
    "name": "Backbone.js",
    "builtwith": true,
    "wappalyzer": true,
    "category": "JavaScript library"
  },
  {
    "id": "background-sound",
    "name": "Background Sound",
    "builtwith": true
  },
  {
    "id": "big-ip",
    "name": "BIG-IP",
    "builtwith": true
  },
  {
    "id": "blackbaud",
    "name": "Blackbaud",
    "builtwith": true
  },
  {
    "id": "blink-element",
    "name": "Blink Element",
    "builtwith": true
  },
  {
    "id": "blogger",
    "name": "Blogger",
    "builtwith": true
  },
  {
    "id": "bloomreach",
    "name": "Bloomreach",
    "wappalyzer": true
  },
  {
    "id": "blueconic",
    "name": "BlueConic",
    "builtwith": true
  },
  {
    "id": "bootstrap",
    "name": "Bootstrap",
    "wappalyzer": true,
    "category": "ui frameworks"
  },
  {
    "name": "Bootstrap 2.3.*",
    "builtwith": true,
    "alias": "bootstrap",
    "category": "ui frameworks"
  },
  {
    "name": "Bootstrap 3.3.*",
    "builtwith": true,
    "alias": "bootstrap",
    "category": "ui frameworks"
  },
  {
    "name": "Bootstrap 3.4.*",
    "builtwith": true,
    "alias": "bootstrap",
    "category": "ui frameworks"
  },
  {
    "name": "Bootstrap 4.1.*",
    "builtwith": true,
    "alias": "bootstrap",
    "category": "ui frameworks"
  },
  {
    "id": "box-over",
    "name": "Box Over",
    "builtwith": true
  },
  {
    "id": "brightcove",
    "name": "Brightcove",
    "builtwith": true
  },
  {
    "id": "brightedge",
    "name": "BrightEdge",
    "builtwith": true
  },
  {
    "id": "browse-happy",
    "name": "Browse Happy",
    "builtwith": true
  },
  {
    "id": "browser-update",
    "name": "Browser-Update",
    "builtwith": true
  },
  {
    "id": "buysellads",
    "name": "BuySellAds",
    "wappalyzer": true
  },
  {
    "id": "bxslider",
    "name": "bxSlider",
    "builtwith": true
  },
  {
    "id": "cache-control",
    "name": "Cache Control",
    "builtwith": true
  },
  {
    "id": "campaignmonitor",
    "name": "Campaign Monitor",
    "builtwith": true
  },
  {
    "name": "Campaign Monitor Widget",
    "builtwith": true,
    "alias": "campaignmonitor"
  },
  {
    "id": "canonical-content-tag",
    "name": "Canonical Content Tag",
    "builtwith": true
  },
  {
    "id": "carbon-ads",
    "name": "Carbon Ads",
    "wappalyzer": true
  },
  {
    "id": "caroufredsel",
    "name": "carouFredSel",
    "builtwith": true
  },
  {
    "id": "cart-functionality",
    "name": "Cart Functionality",
    "wappalyzer": true
  },
  {
    "id": "css",
    "name": "Cascading Style Sheets",
    "builtwith": true,
    "category": "css"
  },
  {
    "id": "cashnet",
    "name": "Cashnet",
    "builtwith": true
  },
  {
    "id": "cdn-js",
    "name": "CDN JS",
    "builtwith": true,
    "category": "cdn"
  },
  {
    "id": "centos",
    "name": "CentOS",
    "builtwith": true
  },
  {
    "id": "chart-js",
    "name": "Chart.js",
    "wappalyzer": true,
    "category": "JavaScript library"
  },
  {
    "id": "chartbeat",
    "name": "Chartbeat",
    "builtwith": true,
    "wappalyzer": true
  },
  {
    "id": "cisco-arrowpoint-content-service-switch",
    "name": "Cisco/Arrowpoint Content Service Switch",
    "builtwith": true
  },
  {
    "id": "citrix-netscaler",
    "name": "Citrix NetScaler",
    "builtwith": true
  },
  {
    "id": "ckeditor",
    "name": "CKEditor",
    "builtwith": true,
    "wappalyzer": true
  },
  {
    "id": "clarivate",
    "name": "Clarivate",
    "builtwith": true
  },
  {
    "id": "clickheat",
    "name": "Clickheat",
    "builtwith": true,
    "wappalyzer": true
  },
  {
    "id": "clicky",
    "name": "Clicky",
    "builtwith": true
  },
  {
    "id": "clipboard-js",
    "name": "Clipboard.js",
    "wappalyzer": true,
    "category": "JavaScript library"
  },
  {
    "id": "cloudflare-js",
    "name": "Cloudflare JS",
    "builtwith": true,
    "category": "JavaScript library"
  },
  {
    "id": "cloudfront",
    "name": "CloudFront",
    "builtwith": true
  },
  {
    "id": "cludo",
    "name": "Cludo",
    "builtwith": true
  },
  {
    "id": "codemirror",
    "name": "CodeMirror",
    "builtwith": true
  },
  {
    "id": "collegeoruniversity-schema",
    "name": "CollegeOrUniversity Schema",
    "builtwith": true
  },
  {
    "id": "concrete5",
    "name": "Concrete5",
    "builtwith": true,
    "wappalyzer": true
  },
  {
    "id": "conditional-comments",
    "name": "Conditional Comments",
    "builtwith": true
  },
  {
    "id": "constant-contact",
    "name": "Constant Contact",
    "builtwith": true
  },
  {
    "id": "contact-form-7",
    "name": "Contact Form 7",
    "builtwith": true
  },
  {
    "id": "contactpoint-schema",
    "name": "ContactPoint Schema",
    "builtwith": true
  },
  {
    "id": "cdn",
    "name": "Content Delivery Network",
    "builtwith": true,
    "category": "cdn"
  },
  {
    "id": "content-security-policy",
    "name": "Content Security Policy",
    "builtwith": true
  },
  {
    "id": "content-style-type",
    "name": "Content Style Type",
    "builtwith": true
  },
  {
    "id": "content-type-options",
    "name": "Content Type Options",
    "builtwith": true
  },
  {
    "id": "convio",
    "name": "Convio",
    "builtwith": true
  },
  {
    "id": "cookie-consent-by-osano",
    "name": "Cookie Consent by Osano",
    "builtwith": true
  },
  {
    "id": "cookie-notice",
    "name": "Cookie Notice",
    "builtwith": true
  },
  {
    "id": "cors",
    "name": "CORS",
    "builtwith": true
  },
  {
    "id": "crazy-egg",
    "name": "Crazy Egg",
    "wappalyzer": true
  },
  {
    "name": "CrazyEgg",
    "builtwith": true,
    "alias": "crazy-egg"
  },
  {
    "id": "createjs",
    "name": "CreateJS",
    "builtwith": true
  },
  {
    "id": "creative-commons",
    "name": "Creative Commons",
    "builtwith": true
  },
  {
    "id": "creativework-schema",
    "name": "CreativeWork Schema",
    "builtwith": true
  },
  {
    "id": "css3-mediaqueries-js",
    "name": "css3-mediaqueries.js",
    "builtwith": true,
    "category": "JavaScript library"
  },
  {
    "id": "cufon",
    "name": "cufón",
    "builtwith": true
  },
  {
    "id": "datatables",
    "name": "DataTables",
    "builtwith": true,
    "wappalyzer": true
  },
  {
    "id": "dav",
    "name": "DAV",
    "builtwith": true
  },
  {
    "id": "day-js",
    "name": "Day.js",
    "builtwith": true,
    "wappalyzer": true,
    "category": "JavaScript library"
  },
  {
    "id": "debian",
    "name": "Debian",
    "builtwith": true,
    "category": "os"
  },
  {
    "name": "Debian Lennny",
    "builtwith": true,
    "alias": "debian",
    "category": "os"
  },
  {
    "id": "deepmetrix",
    "name": "DeepMetrix",
    "builtwith": true
  },
  {
    "id": "delicious",
    "name": "Del.icio.us",
    "builtwith": true
  },
  {
    "id": "digg",
    "name": "Digg",
    "builtwith": true
  },
  {
    "id": "disqus",
    "name": "Disqus",
    "wappalyzer": true
  },
  {
    "id": "divi",
    "name": "Divi",
    "builtwith": true
  },
  {
    "id": "dnn",
    "name": "DNN",
    "wappalyzer": true
  },
  {
    "name": "DNN Software",
    "builtwith": true,
    "alias": "dnn"
  },
  {
    "id": "dns-prefetch",
    "name": "DNS Prefetch",
    "builtwith": true
  },
  {
    "id": "document-class",
    "name": "Document Class",
    "builtwith": true
  },
  {
    "id": "document-rights",
    "name": "Document Rights",
    "builtwith": true
  },
  {
    "id": "dojo",
    "name": "Dojo",
    "wappalyzer": true
  },
  {
    "name": "Dojo Toolkit",
    "builtwith": true,
    "alias": "dojo"
  },
  {
    "id": "dotcms",
    "name": "dotCMS",
    "builtwith": true
  },
  {
    "id": "doubleclick-floodlight",
    "name": "DoubleClick Floodlight",
    "builtwith": true
  },
  {
    "id": "doubleclick-net",
    "name": "DoubleClick.Net",
    "builtwith": true
  },
  {
    "id": "dreamweaver",
    "name": "DreamWeaver",
    "wappalyzer": true
  },
  {
    "id": "drupal",
    "name": "Drupal",
    "builtwith": true,
    "wappalyzer": true
  },
  {
    "name": "Drupal 7",
    "builtwith": true,
    "alias": "drupal"
  },
  {
    "name": "Drupal 8",
    "builtwith": true,
    "alias": "drupal"
  },
  {
    "id": "dstillery",
    "name": "Dstillery",
    "builtwith": true
  },
  {
    "id": "dublin-core",
    "name": "Dublin Core",
    "builtwith": true,
    "category": "metadata"
  },
  {
    "id": "duda",
    "name": "Duda",
    "wappalyzer": true
  },
  {
    "id": "dynatrace",
    "name": "Dynatrace",
    "builtwith": true
  },
  {
    "id": "eab",
    "name": "EAB",
    "builtwith": true
  },
  {
    "id": "easy-pie-chart",
    "name": "Easy Pie Chart",
    "builtwith": true
  },
  {
    "id": "ecmascript-5-shim",
    "name": "ECMAScript 5 Shim",
    "builtwith": true
  },
  {
    "id": "educationalorganization-schema",
    "name": "EducationalOrganization Schema",
    "builtwith": true
  },
  {
    "id": "ektron",
    "name": "Ektron",
    "builtwith": true
  },
  {
    "id": "elsevier",
    "name": "Elsevier",
    "builtwith": true
  },
  {
    "id": "ember-js",
    "name": "Ember",
    "category": "JavaScript library"
  },
  {
    "id": "emma-inc",
    "name": "Emma Inc",
    "builtwith": true
  },
  {
    "id": "endeca",
    "name": "Endeca",
    "builtwith": true
  },
  {
    "id": "enquire-js",
    "name": "Enquire JS",
    "builtwith": true,
    "category": "JavaScript library"
  },
  {
    "id": "enyo",
    "name": "Enyo",
    "wappalyzer": true
  },
  {
    "id": "equal-heights",
    "name": "Equal Heights",
    "builtwith": true
  },
  {
    "id": "ethnio",
    "name": "Ethnio",
    "builtwith": true
  },
  {
    "id": "euro",
    "name": "Euro",
    "builtwith": true
  },
  {
    "id": "event-schema",
    "name": "Event Schema",
    "builtwith": true
  },
  {
    "id": "eventon",
    "name": "EventOn",
    "builtwith": true
  },
  {
    "id": "everyaction",
    "name": "EveryAction",
    "builtwith": true
  },
  {
    "id": "ex-libris",
    "name": "Ex Libris",
    "builtwith": true
  },
  {
    "id": "exhibit",
    "name": "Exhibit",
    "wappalyzer": true
  },
  {
    "id": "explorer-canvas",
    "name": "Explorer Canvas",
    "builtwith": true
  },
  {
    "id": "ext-js",
    "name": "Ext JS",
    "builtwith": true,
    "category": "JavaScript library"
  },
  {
    "id": "facebook",
    "name": "Facebook",
    "wappalyzer": true
  },
  {
    "name": "Facebook Badge",
    "builtwith": true,
    "alias": "facebook"
  },
  {
    "id": "facebook-conversion-tracking",
    "name": "Facebook Conversion Tracking",
    "builtwith": true
  },
  {
    "id": "facebook-custom-audiences",
    "name": "Facebook Custom Audiences",
    "builtwith": true
  },
  {
    "id": "facebook-domain-insights",
    "name": "Facebook Domain Insights",
    "builtwith": true
  },
  {
    "name": "Facebook for Websites",
    "builtwith": true,
    "alias": "facebook"
  },
  {
    "id": "facebook-graph-api",
    "name": "Facebook Graph API",
    "builtwith": true
  },
  {
    "name": "Facebook Like",
    "builtwith": true,
    "alias": "facebook"
  },
  {
    "name": "Facebook Like Box",
    "builtwith": true,
    "alias": "facebook"
  },
  {
    "name": "Facebook Like Button",
    "builtwith": true,
    "alias": "facebook"
  },
  {
    "id": "facebook-page-administration",
    "name": "Facebook Page Administration",
    "builtwith": true
  },
  {
    "id": "facebook-pixel",
    "name": "Facebook Pixel",
    "builtwith": true
  },
  {
    "name": "Facebook Pixel View Content",
    "builtwith": true,
    "alias": "facebook"
  },
  {
    "id": "facebook-sdk",
    "name": "Facebook SDK",
    "builtwith": true
  },
  {
    "id": "facebook-sharer",
    "name": "Facebook Sharer",
    "builtwith": true
  },
  {
    "id": "facebook-sign-in",
    "name": "Facebook Sign-in",
    "wappalyzer": true
  },
  {
    "id": "fancybox",
    "name": "Fancybox",
    "builtwith": true,
    "wappalyzer": true
  },
  {
    "id": "featherlight",
    "name": "Featherlight",
    "builtwith": true
  },
  {
    "id": "feature-policy",
    "name": "Feature Policy",
    "builtwith": true
  },
  {
    "id": "fedora",
    "name": "Fedora",
    "builtwith": true
  },
  {
    "id": "feedburner",
    "name": "FeedBurner",
    "builtwith": true
  },
  {
    "id": "feedwind",
    "name": "FeedWind",
    "builtwith": true
  },
  {
    "id": "fingerprintjs",
    "name": "Fingerprintjs",
    "wappalyzer": true
  },
  {
    "id": "fitvids-js",
    "name": "FitVids.JS",
    "builtwith": true,
    "category": "JavaScript library"
  },
  {
    "name": "Flash Object",
    "builtwith": true,
    "alias": "flash"
  },
  {
    "id": "flexslider",
    "name": "FlexSlider",
    "builtwith": true,
    "wappalyzer": true
  },
  {
    "id": "flickity",
    "name": "Flickity",
    "wappalyzer": true
  },
  {
    "id": "flickr-badge",
    "name": "Flickr Badge",
    "builtwith": true
  },
  {
    "id": "flickr-photostream",
    "name": "Flickr PhotoStream",
    "builtwith": true
  },
  {
    "id": "flowplayer",
    "name": "Flowplayer",
    "builtwith": true
  },
  {
    "id": "flv-player",
    "name": "FLV Player",
    "builtwith": true
  },
  {
    "id": "foaf",
    "name": "FOAF",
    "builtwith": true
  },
  {
    "id": "font-awesome",
    "name": "Font Awesome",
    "builtwith": true,
    "wappalyzer": true,
    "category": "fonts"
  },
  {
    "id": "fontdeck",
    "name": "Fontdeck",
    "builtwith": true,
    "category": "fonts"
  },
  {
    "id": "fonts-com",
    "name": "Fonts.com",
    "builtwith": true,
    "category": "fonts"
  },
  {
    "id": "foresee-results",
    "name": "ForeSee Results",
    "builtwith": true
  },
  {
    "id": "formalize-css",
    "name": "Formalize CSS",
    "builtwith": true,
    "category": "css"
  },
  {
    "id": "formidable-pro-form",
    "name": "Formidable Pro Form",
    "builtwith": true
  },
  {
    "id": "formstack",
    "name": "Formstack",
    "builtwith": true
  },
  {
    "id": "foundation",
    "name": "Foundation",
    "builtwith": true
  },
  {
    "id": "frameset",
    "name": "Frameset",
    "builtwith": true
  },
  {
    "id": "freebsd",
    "name": "FreeBSD",
    "builtwith": true
  },
  {
    "id": "friends-network",
    "name": "Friends Network",
    "builtwith": true
  },
  {
    "id": "frontpage",
    "name": "FrontPage",
    "wappalyzer": true
  },
  {
    "name": "Frontpage Extensions",
    "builtwith": true,
    "alias": "frontpage"
  },
  {
    "name": "Frontpage Proprietary Tags",
    "builtwith": true,
    "alias": "frontpage"
  },
  {
    "id": "froogaloop",
    "name": "Froogaloop",
    "builtwith": true
  },
  {
    "id": "fullcalendar",
    "name": "FullCalendar",
    "builtwith": true
  },
  {
    "id": "gatsby",
    "name": "Gatsby",
    "wappalyzer": true,
    "category": "JavaScript library"
  },
  {
    "name": "Gatsby JS",
    "builtwith": true,
    "alias": "gatsby",
    "category": "JavaScript library"
  },
  {
    "id": "gaug-es",
    "name": "Gaug.es",
    "builtwith": true
  },
  {
    "id": "gauges",
    "name": "Gauges",
    "wappalyzer": true
  },
  {
    "id": "geocoordinates-schema",
    "name": "GeoCoordinates Schema",
    "builtwith": true
  },
  {
    "id": "geographic-information",
    "name": "Geographic Information",
    "builtwith": true
  },
  {
    "id": "global-site-tag",
    "name": "Global Site Tag",
    "builtwith": true
  },
  {
    "id": "globalsign-domain-verification",
    "name": "GlobalSign Domain Verification",
    "builtwith": true
  },
  {
    "id": "glyphicons",
    "name": "Glyphicons",
    "wappalyzer": true,
    "category": "icons"
  },
  {
    "id": "gnu-terry-pratchett",
    "name": "GNU Terry Pratchett",
    "builtwith": true
  },
  {
    "name": "GoLive Javascript",
    "builtwith": true,
    "alias": "adobe-golive"
  },
  {
    "id": "google-adsense-for-search",
    "name": "Google Adsense for Search",
    "builtwith": true
  },
  {
    "id": "google-adwords-conversion",
    "name": "Google AdWords Conversion",
    "builtwith": true
  },
  {
    "id": "google-analyticator",
    "name": "Google Analyticator",
    "builtwith": true
  },
  {
    "id": "google-analytics",
    "name": "Google Analytics",
    "builtwith": true,
    "wappalyzer": true
  },
  {
    "name": "Google Analytics Anonymize IP",
    "builtwith": true,
    "alias": "google-analytics"
  },
  {
    "name": "Google Analytics Classic",
    "builtwith": true,
    "alias": "google-analytics"
  },
  {
    "name": "Google Analytics Dashboard for WordPress",
    "builtwith": true,
    "alias": "google-analytics"
  },
  {
    "name": "Google Analytics Enhanced eCommerce",
    "wappalyzer": true,
    "alias": "google-analytics"
  },
  {
    "name": "Google Analytics Enhanced Link Attribution",
    "builtwith": true,
    "alias": "google-analytics"
  },
  {
    "name": "Google Analytics Event Tracking",
    "builtwith": true,
    "alias": "google-analytics"
  },
  {
    "name": "Google Analytics Forced SSL",
    "builtwith": true,
    "alias": "google-analytics"
  },
  {
    "name": "Google Analytics IP Anonymization",
    "builtwith": true,
    "alias": "google-analytics"
  },
  {
    "name": "Google Analytics Multiple Trackers",
    "builtwith": true,
    "alias": "google-analytics"
  },
  {
    "name": "Google Analytics with Ad Tracking",
    "builtwith": true,
    "alias": "google-analytics"
  },
  {
    "id": "google-api",
    "name": "Google API",
    "builtwith": true
  },
  {
    "id": "google-calendar",
    "name": "Google Calendar",
    "builtwith": true
  },
  {
    "id": "google-charts",
    "name": "Google Charts",
    "builtwith": true
  },
  {
    "id": "google-chrome-frame-popup",
    "name": "Google Chrome Frame Popup",
    "builtwith": true
  },
  {
    "id": "google-chrome-ie-frame",
    "name": "Google Chrome IE Frame",
    "builtwith": true
  },
  {
    "id": "google-code-prettify",
    "name": "Google Code Prettify",
    "wappalyzer": true
  },
  {
    "id": "google-conversion-tracking",
    "name": "Google Conversion Tracking",
    "builtwith": true
  },
  {
    "id": "google-custom-search",
    "name": "Google Custom Search",
    "builtwith": true
  },
  {
    "id": "google-docs-widget",
    "name": "Google Docs Widget",
    "builtwith": true
  },
  {
    "id": "google-feedproxy",
    "name": "Google FeedProxy",
    "builtwith": true
  },
  {
    "id": "google-font-api",
    "name": "Google Font API",
    "builtwith": true,
    "wappalyzer": true,
    "category": "fonts"
  },
  {
    "id": "google-front-end",
    "name": "Google Front End",
    "builtwith": true
  },
  {
    "name": "Google Hosted jQuery",
    "builtwith": true,
    "alias": "jquery"
  },
  {
    "name": "Google Hosted jQuery UI",
    "builtwith": true,
    "alias": "jquery-ui"
  },
  {
    "id": "google-hosted-libraries",
    "name": "Google Hosted Libraries",
    "builtwith": true
  },
  {
    "name": "Google Hosted SWFObject",
    "builtwith": true,
    "alias": "flash"
  },
  {
    "id": "google-hosted-web-font-loader",
    "name": "Google Hosted Web Font Loader",
    "builtwith": true,
    "category": "fonts"
  },
  {
    "id": "google-js-api",
    "name": "Google JS Api",
    "builtwith": true
  },
  {
    "id": "google-maps",
    "name": "Google Maps",
    "builtwith": true,
    "wappalyzer": true
  },
  {
    "name": "Google Maps API",
    "builtwith": true,
    "alias": "google-maps"
  },
  {
    "name": "Google Maps for Work",
    "builtwith": true,
    "alias": "google-maps"
  },
  {
    "id": "google-optimize-360",
    "name": "Google Optimize 360",
    "builtwith": true
  },
  {
    "id": "google-plus",
    "name": "Google Plus",
    "wappalyzer": true
  },
  {
    "id": "google-plus-one-publisher",
    "name": "Google Plus One Publisher",
    "builtwith": true
  },
  {
    "id": "google-plus-one-snippet",
    "name": "Google Plus One Snippet",
    "builtwith": true
  },
  {
    "id": "google-remarketing",
    "name": "Google Remarketing",
    "builtwith": true
  },
  {
    "id": "google-search-appliance",
    "name": "Google Search Appliance",
    "builtwith": true
  },
  {
    "id": "google-sites",
    "name": "Google Sites",
    "builtwith": true
  },
  {
    "id": "google-tag-manager",
    "name": "Google Tag Manager",
    "builtwith": true,
    "wappalyzer": true
  },
  {
    "id": "google-translate",
    "name": "Google Translate"
  },
  {
    "name": "Google Translate Widget",
    "builtwith": true,
    "alias": "google-translate"
  },
  {
    "name": "Google Universal Analytics",
    "builtwith": true,
    "alias": "google-analytics"
  },
  {
    "id": "google-webmaster",
    "name": "Google Webmaster",
    "builtwith": true
  },
  {
    "id": "gravity-forms",
    "name": "Gravity Forms",
    "builtwith": true,
    "wappalyzer": true
  },
  {
    "id": "gsap",
    "name": "GSAP",
    "builtwith": true,
    "wappalyzer": true
  },
  {
    "id": "gstatic-google-static-content",
    "name": "GStatic Google Static Content",
    "builtwith": true
  },
  {
    "id": "gzip-module",
    "name": "GZIP Module",
    "builtwith": true
  },
  {
    "id": "hammer-js",
    "name": "Hammer.js",
    "wappalyzer": true,
    "category": "JavaScript library"
  },
  {
    "id": "handheld-friendly",
    "name": "Handheld Friendly",
    "builtwith": true
  },
  {
    "id": "handlebars",
    "name": "Handlebars",
    "builtwith": true,
    "wappalyzer": true
  },
  {
    "id": "headjs",
    "name": "HeadJS",
    "wappalyzer": true,
    "category": "JavaScript library"
  },
  {
    "id": "heatmap-it",
    "name": "Heatmap IT",
    "builtwith": true
  },
  {
    "id": "hier-menus",
    "name": "Hier Menus",
    "builtwith": true
  },
  {
    "id": "highlight-js",
    "name": "Highlight.js",
    "wappalyzer": true,
    "category": "JavaScript library"
  },
  {
    "id": "hippo",
    "name": "Hippo",
    "builtwith": true
  },
  {
    "id": "histats",
    "name": "Histats",
    "builtwith": true
  },
  {
    "id": "hitslink",
    "name": "Hitslink",
    "builtwith": true
  },
  {
    "id": "hotjar",
    "name": "Hotjar",
    "builtwith": true,
    "wappalyzer": true
  },
  {
    "id": "hover-intent",
    "name": "Hover Intent",
    "builtwith": true
  },
  {
    "id": "hsts",
    "name": "HSTS",
    "builtwith": true
  },
  {
    "id": "hsts-includesubdomains-preload",
    "name": "HSTS IncludeSubdomains PreLoad",
    "builtwith": true
  },
  {
    "id": "html4",
    "name": "HTML 4 / 4.01 Strict",
    "builtwith": true,
    "category": "html"
  },
  {
    "name": "HTML 4.01 Transitional DTD",
    "builtwith": true,
    "alias": "html4",
    "category": "html"
  },
  {
    "name": "HTML 5 Specific Tags",
    "builtwith": true,
    "alias": "html5",
    "category": "html"
  },
  {
    "name": "HTML 5 Video Audio Tags",
    "builtwith": true,
    "alias": "html5",
    "category": "html"
  },
  {
    "id": "html-imports",
    "name": "HTML Imports",
    "builtwith": true,
    "category": "html"
  },
  {
    "id": "html-tidy",
    "name": "HTML Tidy",
    "builtwith": true,
    "category": "html"
  },
  {
    "id": "html5-boilerplate",
    "name": "HTML5 Boilerplate",
    "builtwith": true,
    "category": "html"
  },
  {
    "id": "html5",
    "name": "HTML5 DocType",
    "builtwith": true,
    "category": "html"
  },
  {
    "name": "HTML5 History API",
    "builtwith": true,
    "alias": "html5",
    "category": "html"
  },
  {
    "id": "html5shiv",
    "name": "html5shiv",
    "builtwith": true,
    "category": "JavaScript library"
  },
  {
    "id": "hubspot",
    "name": "Hubspot",
    "builtwith": true,
    "wappalyzer": true
  },
  {
    "id": "hubspot-forms",
    "name": "Hubspot Forms",
    "builtwith": true
  },
  {
    "id": "hugo",
    "name": "Hugo",
    "builtwith": true,
    "wappalyzer": true
  },
  {
    "id": "humans-txt",
    "name": "Humans TXT",
    "builtwith": true
  },
  {
    "id": "ibm-http-server",
    "name": "IBM HTTP Server",
    "builtwith": true,
    "category": "servers"
  },
  {
    "id": "ie7-js",
    "name": "ie7-js",
    "builtwith": true,
    "category": "JavaScript library"
  },
  {
    "id": "iframe",
    "name": "IFrame",
    "builtwith": true
  },
  {
    "id": "iis",
    "name": "IIS",
    "builtwith": true,
    "wappalyzer": true,
    "category": "servers"
  },
  {
    "name": "IIS 10",
    "builtwith": true,
    "alias": "iis",
    "category": "servers"
  },
  {
    "name": "IIS 3",
    "builtwith": true,
    "alias": "iis",
    "category": "servers"
  },
  {
    "name": "IIS 4",
    "builtwith": true,
    "alias": "iis",
    "category": "servers"
  },
  {
    "name": "IIS 5",
    "builtwith": true,
    "alias": "iis",
    "category": "servers"
  },
  {
    "name": "IIS 6",
    "builtwith": true,
    "alias": "iis",
    "category": "servers"
  },
  {
    "name": "IIS 7",
    "builtwith": true,
    "alias": "iis",
    "category": "servers"
  },
  {
    "name": "IIS 8",
    "builtwith": true,
    "alias": "iis",
    "category": "servers"
  },
  {
    "id": "image-map",
    "name": "Image Map",
    "builtwith": true
  },
  {
    "id": "image-tool-bar",
    "name": "Image Tool Bar",
    "builtwith": true
  },
  {
    "id": "imagesloaded",
    "name": "imagesLoaded",
    "builtwith": true
  },
  {
    "id": "imgix",
    "name": "Imgix",
    "builtwith": true
  },
  {
    "id": "imgur",
    "name": "Imgur",
    "builtwith": true
  },
  {
    "id": "imodules",
    "name": "iModules",
    "builtwith": true
  },
  {
    "id": "incapsula-cdn",
    "name": "Incapsula CDN",
    "builtwith": true,
    "category": "cdn"
  },
  {
    "id": "infinite-scroll",
    "name": "Infinite Scroll",
    "builtwith": true
  },
  {
    "id": "informer",
    "name": "Informer",
    "builtwith": true
  },
  {
    "id": "inspectlet",
    "name": "Inspectlet",
    "builtwith": true,
    "wappalyzer": true
  },
  {
    "id": "instafeed-js",
    "name": "Instafeed.js",
    "builtwith": true,
    "category": "JavaScript library"
  },
  {
    "id": "ipad-compatible",
    "name": "iPad Compatible",
    "builtwith": true
  },
  {
    "id": "iphone-mobile-compatible",
    "name": "IPhone / Mobile Compatible",
    "builtwith": true
  },
  {
    "id": "ironpoint",
    "name": "IronPoint",
    "builtwith": true
  },
  {
    "id": "iso-iec-8859",
    "name": "ISO/IEC 8859",
    "builtwith": true
  },
  {
    "id": "isotope",
    "name": "Isotope",
    "builtwith": true
  },
  {
    "id": "java",
    "name": "Java",
    "wappalyzer": true
  },
  {
    "name": "Java EE",
    "builtwith": true,
    "alias": "java"
  },
  {
    "name": "Java Servlet",
    "builtwith": true,
    "alias": "java"
  },
  {
    "id": "javascript",
    "name": "Javascript",
    "builtwith": true
  },
  {
    "id": "javascript-defer",
    "name": "Javascript Defer",
    "builtwith": true
  },
  {
    "id": "javascript-infovis-toolkit",
    "name": "JavaScript Infovis Toolkit",
    "wappalyzer": true
  },
  {
    "id": "javascript-tooltips",
    "name": "Javascript Tooltips",
    "builtwith": true
  },
  {
    "id": "jboss",
    "name": "JBoss",
    "builtwith": true
  },
  {
    "id": "jcarousel",
    "name": "JCarousel",
    "builtwith": true
  },
  {
    "id": "jcarousel-lite",
    "name": "JCarousel Lite",
    "builtwith": true
  },
  {
    "id": "jetpack",
    "name": "Jetpack",
    "builtwith": true
  },
  {
    "id": "jetty",
    "name": "Jetty",
    "builtwith": true
  },
  {
    "id": "joomla",
    "name": "Joomla",
    "wappalyzer": true
  },
  {
    "name": "Joomla!",
    "builtwith": true,
    "alias": "joomla"
  },
  {
    "id": "jotform",
    "name": "JotForm",
    "builtwith": true
  },
  {
    "id": "jqbootstrapvalidation",
    "name": "jqBootstrapValidation",
    "builtwith": true
  },
  {
    "id": "jquery",
    "name": "jQuery",
    "builtwith": true,
    "wappalyzer": true,
    "category": "JavaScript library"
  },
  {
    "name": "jQuery 1.10.0",
    "builtwith": true,
    "alias": "jquery",
    "category": "JavaScript library"
  },
  {
    "name": "jQuery 1.10.1",
    "builtwith": true,
    "alias": "jquery",
    "category": "JavaScript library"
  },
  {
    "name": "jQuery 1.10.2",
    "builtwith": true,
    "alias": "jquery",
    "category": "JavaScript library"
  },
  {
    "name": "jQuery 1.11.0",
    "builtwith": true,
    "alias": "jquery",
    "category": "JavaScript library"
  },
  {
    "name": "jQuery 1.11.1",
    "builtwith": true,
    "alias": "jquery",
    "category": "JavaScript library"
  },
  {
    "name": "jQuery 1.11.2",
    "builtwith": true,
    "alias": "jquery",
    "category": "JavaScript library"
  },
  {
    "name": "jQuery 1.11.3",
    "builtwith": true,
    "alias": "jquery",
    "category": "JavaScript library"
  },
  {
    "name": "jQuery 1.12.0",
    "builtwith": true,
    "alias": "jquery",
    "category": "JavaScript library"
  },
  {
    "name": "jQuery 1.12.3",
    "builtwith": true,
    "alias": "jquery",
    "category": "JavaScript library"
  },
  {
    "name": "jQuery 1.12.4",
    "builtwith": true,
    "alias": "jquery",
    "category": "JavaScript library"
  },
  {
    "name": "jQuery 1.2.6",
    "builtwith": true,
    "alias": "jquery",
    "category": "JavaScript library"
  },
  {
    "name": "jQuery 1.3.1",
    "builtwith": true,
    "alias": "jquery",
    "category": "JavaScript library"
  },
  {
    "name": "jQuery 1.3.2",
    "builtwith": true,
    "alias": "jquery",
    "category": "JavaScript library"
  },
  {
    "name": "jQuery 1.4",
    "builtwith": true,
    "alias": "jquery",
    "category": "JavaScript library"
  },
  {
    "name": "jQuery 1.4.2",
    "builtwith": true,
    "alias": "jquery",
    "category": "JavaScript library"
  },
  {
    "name": "jQuery 1.4.3",
    "builtwith": true,
    "alias": "jquery",
    "category": "JavaScript library"
  },
  {
    "name": "jQuery 1.4.4",
    "builtwith": true,
    "alias": "jquery",
    "category": "JavaScript library"
  },
  {
    "name": "jQuery 1.5.1",
    "builtwith": true,
    "alias": "jquery",
    "category": "JavaScript library"
  },
  {
    "name": "jQuery 1.5.2",
    "builtwith": true,
    "alias": "jquery",
    "category": "JavaScript library"
  },
  {
    "name": "jQuery 1.6",
    "builtwith": true,
    "alias": "jquery",
    "category": "JavaScript library"
  },
  {
    "name": "jQuery 1.6.2",
    "builtwith": true,
    "alias": "jquery",
    "category": "JavaScript library"
  },
  {
    "name": "jQuery 1.6.3",
    "builtwith": true,
    "alias": "jquery",
    "category": "JavaScript library"
  },
  {
    "name": "jQuery 1.6.4",
    "builtwith": true,
    "alias": "jquery",
    "category": "JavaScript library"
  },
  {
    "name": "jQuery 1.7",
    "builtwith": true,
    "alias": "jquery",
    "category": "JavaScript library"
  },
  {
    "name": "jQuery 1.7.0",
    "builtwith": true,
    "alias": "jquery",
    "category": "JavaScript library"
  },
  {
    "name": "jQuery 1.7.1",
    "builtwith": true,
    "alias": "jquery",
    "category": "JavaScript library"
  },
  {
    "name": "jQuery 1.7.2",
    "builtwith": true,
    "alias": "jquery",
    "category": "JavaScript library"
  },
  {
    "name": "jQuery 1.8.0",
    "builtwith": true,
    "alias": "jquery",
    "category": "JavaScript library"
  },
  {
    "name": "jQuery 1.8.1",
    "builtwith": true,
    "alias": "jquery",
    "category": "JavaScript library"
  },
  {
    "name": "jQuery 1.8.2",
    "builtwith": true,
    "alias": "jquery",
    "category": "JavaScript library"
  },
  {
    "name": "jQuery 1.8.3",
    "builtwith": true,
    "alias": "jquery",
    "category": "JavaScript library"
  },
  {
    "name": "jQuery 1.9.0",
    "builtwith": true,
    "alias": "jquery",
    "category": "JavaScript library"
  },
  {
    "name": "jQuery 1.9.1",
    "builtwith": true,
    "alias": "jquery",
    "category": "JavaScript library"
  },
  {
    "name": "jQuery 2.1.0",
    "builtwith": true,
    "alias": "jquery",
    "category": "JavaScript library"
  },
  {
    "name": "jQuery 2.1.1",
    "builtwith": true,
    "alias": "jquery",
    "category": "JavaScript library"
  },
  {
    "name": "jQuery 2.1.3",
    "builtwith": true,
    "alias": "jquery",
    "category": "JavaScript library"
  },
  {
    "name": "jQuery 2.1.4",
    "builtwith": true,
    "alias": "jquery",
    "category": "JavaScript library"
  },
  {
    "name": "jQuery 2.2.0",
    "builtwith": true,
    "alias": "jquery",
    "category": "JavaScript library"
  },
  {
    "name": "jQuery 3.1.0",
    "builtwith": true,
    "alias": "jquery",
    "category": "JavaScript library"
  },
  {
    "name": "jQuery 3.1.1",
    "builtwith": true,
    "alias": "jquery",
    "category": "JavaScript library"
  },
  {
    "name": "jQuery 3.2.1",
    "builtwith": true,
    "alias": "jquery",
    "category": "JavaScript library"
  },
  {
    "name": "jQuery 3.3.1",
    "builtwith": true,
    "alias": "jquery",
    "category": "JavaScript library"
  },
  {
    "name": "jQuery 3.4.1",
    "builtwith": true,
    "alias": "jquery",
    "category": "JavaScript library"
  },
  {
    "name": "jQuery 3.5.1",
    "builtwith": true,
    "alias": "jquery",
    "category": "JavaScript library"
  },
  {
    "id": "jquery-autocomplete",
    "name": "jQuery Autocomplete",
    "builtwith": true,
    "category": "JavaScript library"
  },
  {
    "id": "jquery-bbq",
    "name": "jQuery BBQ",
    "builtwith": true,
    "category": "JavaScript library"
  },
  {
    "id": "jquery-bgiframe",
    "name": "jQuery bgiframe",
    "builtwith": true,
    "category": "JavaScript library"
  },
  {
    "id": "jquery-blockui",
    "name": "jQuery BlockUI",
    "builtwith": true,
    "category": "JavaScript library"
  },
  {
    "id": "jquery-cdn",
    "name": "jQuery CDN",
    "builtwith": true,
    "category": "JavaScript library, cdn"
  },
  {
    "id": "jquery-colorbox",
    "name": "jQuery Colorbox",
    "builtwith": true,
    "category": "JavaScript library"
  },
  {
    "id": "jquery-cookie",
    "name": "jQuery Cookie",
    "builtwith": true,
    "category": "JavaScript library"
  },
  {
    "id": "jquery-countdown",
    "name": "jQuery Countdown",
    "builtwith": true,
    "category": "JavaScript library"
  },
  {
    "id": "jquery-custom-content-scroller",
    "name": "jQuery Custom Content Scroller",
    "builtwith": true,
    "category": "JavaScript library"
  },
  {
    "id": "jquery-cycle",
    "name": "jQuery Cycle",
    "builtwith": true,
    "category": "JavaScript library"
  },
  {
    "id": "jquery-dimensions",
    "name": "jQuery Dimensions",
    "builtwith": true,
    "category": "JavaScript library"
  },
  {
    "id": "jquery-easing",
    "name": "jQuery Easing",
    "builtwith": true,
    "category": "JavaScript library"
  },
  {
    "id": "jquery-flash",
    "name": "jQuery Flash",
    "builtwith": true,
    "category": "JavaScript library"
  },
  {
    "id": "jquery-form",
    "name": "jQuery Form",
    "builtwith": true,
    "category": "JavaScript library"
  },
  {
    "id": "jquery-hotlink",
    "name": "jQuery HotLink",
    "builtwith": true,
    "category": "JavaScript library"
  },
  {
    "id": "jquery-marquee",
    "name": "jQuery Marquee",
    "builtwith": true,
    "category": "JavaScript library"
  },
  {
    "id": "jquery-masonry",
    "name": "jQuery Masonry",
    "builtwith": true,
    "category": "JavaScript library"
  },
  {
    "id": "jquery-metadata",
    "name": "jQuery Metadata",
    "builtwith": true,
    "category": "JavaScript library"
  },
  {
    "id": "jquery-migrate",
    "name": "jQuery Migrate",
    "wappalyzer": true,
    "category": "JavaScript library"
  },
  {
    "id": "jquery-mobile",
    "name": "jQuery Mobile",
    "wappalyzer": true,
    "category": "JavaScript library"
  },
  {
    "id": "jquery-mousewheel",
    "name": "jQuery Mousewheel",
    "builtwith": true,
    "category": "JavaScript library"
  },
  {
    "id": "jquery-noconflict",
    "name": "jQuery NoConflict",
    "builtwith": true,
    "category": "JavaScript library"
  },
  {
    "id": "jquery-once",
    "name": "jQuery Once",
    "builtwith": true,
    "category": "JavaScript library"
  },
  {
    "id": "jquery-placeholder",
    "name": "jQuery Placeholder",
    "builtwith": true,
    "category": "JavaScript library"
  },
  {
    "id": "jquery-pngfix",
    "name": "jQuery pngfix",
    "builtwith": true,
    "category": "JavaScript library"
  },
  {
    "id": "jquery-prettyphoto",
    "name": "jQuery prettyPhoto",
    "builtwith": true,
    "category": "JavaScript library"
  },
  {
    "id": "jquery-qtip",
    "name": "jQuery QTip",
    "builtwith": true,
    "category": "JavaScript library"
  },
  {
    "id": "jquery-quicksand",
    "name": "jQuery QuickSand",
    "builtwith": true,
    "category": "JavaScript library"
  },
  {
    "id": "jquery-scrollto",
    "name": "jQuery ScrollTo",
    "builtwith": true,
    "category": "JavaScript library"
  },
  {
    "id": "jquery-sparklines",
    "name": "jQuery Sparklines",
    "wappalyzer": true,
    "category": "JavaScript library"
  },
  {
    "id": "jquery-tools",
    "name": "jQuery Tools",
    "builtwith": true,
    "category": "JavaScript library"
  },
  {
    "id": "jquery-tooltip",
    "name": "jQuery Tooltip",
    "builtwith": true,
    "category": "JavaScript library"
  },
  {
    "id": "jquery-translate",
    "name": "jQuery Translate",
    "builtwith": true,
    "category": "JavaScript library"
  },
  {
    "id": "jquery-ui",
    "name": "jQuery UI",
    "builtwith": true,
    "wappalyzer": true,
    "category": "JavaScript library"
  },
  {
    "id": "jquery-ui-mouse",
    "name": "jQuery UI Mouse",
    "builtwith": true,
    "category": "JavaScript library"
  },
  {
    "id": "jquery-ui-tabs",
    "name": "jQuery UI Tabs",
    "builtwith": true,
    "category": "JavaScript library"
  },
  {
    "id": "jquery-validate",
    "name": "jQuery Validate",
    "builtwith": true,
    "category": "JavaScript library"
  },
  {
    "id": "jquery-waypoints",
    "name": "jQuery Waypoints",
    "builtwith": true,
    "category": "JavaScript library"
  },
  {
    "id": "jrun",
    "name": "JRun",
    "builtwith": true
  },
  {
    "id": "jscrollpane",
    "name": "jScrollPane",
    "builtwith": true
  },
  {
    "id": "jsdelivr",
    "name": "jsDelivr",
    "builtwith": true,
    "wappalyzer": true
  },
  {
    "id": "json-ld",
    "name": "JSON-LD",
    "builtwith": true
  },
  {
    "id": "jw-player",
    "name": "JW Player",
    "builtwith": true
  },
  {
    "id": "jw-player-tracking",
    "name": "JW Player Tracking",
    "builtwith": true
  },
  {
    "id": "kaltura",
    "name": "Kaltura",
    "builtwith": true
  },
  {
    "id": "kentico-cms",
    "name": "Kentico CMS",
    "wappalyzer": true
  },
  {
    "id": "kentico-xperience",
    "name": "Kentico Xperience",
    "builtwith": true
  },
  {
    "id": "ladda-ui",
    "name": "Ladda UI",
    "builtwith": true
  },
  {
    "id": "lazysizes",
    "name": "lazySizes",
    "builtwith": true
  },
  {
    "id": "libraryh3lp",
    "name": "LibraryH3lp",
    "builtwith": true
  },
  {
    "id": "license-buttons",
    "name": "License Buttons",
    "builtwith": true
  },
  {
    "id": "lightbox",
    "name": "Lightbox",
    "builtwith": true,
    "wappalyzer": true
  },
  {
    "id": "limiter-modules",
    "name": "Limiter Modules",
    "builtwith": true
  },
  {
    "id": "linkedin-ads",
    "name": "LinkedIn Ads",
    "builtwith": true
  },
  {
    "id": "linkedin-insight-tag",
    "name": "Linkedin Insight Tag",
    "wappalyzer": true
  },
  {
    "id": "linkedin-insights",
    "name": "LinkedIn Insights",
    "builtwith": true
  },
  {
    "id": "liquid-web",
    "name": "Liquid Web",
    "builtwith": true
  },
  {
    "id": "list-js",
    "name": "List.js",
    "wappalyzer": true,
    "category": "JavaScript library"
  },
  {
    "id": "live-writer-support",
    "name": "Live Writer Support",
    "builtwith": true
  },
  {
    "id": "livechat",
    "name": "LiveChat",
    "wappalyzer": true
  },
  {
    "id": "liveperson",
    "name": "LivePerson",
    "builtwith": true
  },
  {
    "id": "lodash",
    "name": "lodash",
    "builtwith": true,
    "wappalyzer": true
  },
  {
    "id": "lotus-domino",
    "name": "Lotus Domino",
    "builtwith": true
  },
  {
    "id": "lytebox",
    "name": "Lytebox",
    "builtwith": true
  },
  {
    "id": "m3u-stream",
    "name": "M3U Stream",
    "builtwith": true
  },
  {
    "id": "magnific-popup",
    "name": "Magnific Popup",
    "builtwith": true
  },
  {
    "id": "mailchimp",
    "name": "MailChimp",
    "builtwith": true,
    "wappalyzer": true
  },
  {
    "id": "mailpoet",
    "name": "MailPoet",
    "builtwith": true
  },
  {
    "id": "mambo",
    "name": "Mambo",
    "builtwith": true,
    "wappalyzer": true
  },
  {
    "id": "marin-software",
    "name": "Marin Software",
    "builtwith": true
  },
  {
    "id": "marquee",
    "name": "Marquee",
    "builtwith": true
  },
  {
    "id": "matchmedia",
    "name": "matchMedia",
    "builtwith": true
  },
  {
    "id": "material-design-for-bootstrap",
    "name": "Material Design for Bootstrap",
    "builtwith": true
  },
  {
    "id": "materialize-css",
    "name": "Materialize CSS",
    "builtwith": true,
    "wappalyzer": true,
    "category": "css"
  },
  {
    "id": "matomo",
    "name": "Matomo",
    "builtwith": true
  },
  {
    "id": "matomo-analytics",
    "name": "Matomo Analytics",
    "wappalyzer": true
  },
  {
    "id": "matomo-cloud",
    "name": "Matomo Cloud",
    "builtwith": true
  },
  {
    "id": "matomo-tag-manager",
    "name": "Matomo Tag Manager",
    "builtwith": true,
    "wappalyzer": true
  },
  {
    "id": "matterport",
    "name": "Matterport",
    "builtwith": true
  },
  {
    "id": "mediaelement-js",
    "name": "MediaElement.js",
    "builtwith": true,
    "wappalyzer": true,
    "category": "JavaScript library"
  },
  {
    "id": "mediamind",
    "name": "MediaMind",
    "builtwith": true
  },
  {
    "id": "meebo",
    "name": "Meebo",
    "builtwith": true
  },
  {
    "id": "meta-description",
    "name": "Meta Description",
    "builtwith": true
  },
  {
    "id": "meta-keywords",
    "name": "Meta Keywords",
    "builtwith": true
  },
  {
    "id": "meta-robot",
    "name": "Meta Robot",
    "builtwith": true
  },
  {
    "id": "microdata",
    "name": "Microdata",
    "builtwith": true
  },
  {
    "id": "microsoft-ajax-content-delivery-network",
    "name": "Microsoft Ajax Content Delivery Network",
    "builtwith": true
  },
  {
    "id": "microsoft-asp-net",
    "name": "Microsoft ASP.NET",
    "wappalyzer": true
  },
  {
    "id": "microsoft-azure",
    "name": "Microsoft Azure"
  },
  {
    "name": "Microsoft Azure Blob Storage",
    "builtwith": true,
    "alias": "microsoft-azure"
  },
  {
    "id": "microsoft-frontpage",
    "name": "Microsoft Frontpage",
    "builtwith": true
  },
  {
    "id": "microsoft-office",
    "name": "Microsoft Office",
    "builtwith": true
  },
  {
    "id": "microsoft-office-sharepoint",
    "name": "Microsoft Office SharePoint",
    "builtwith": true
  },
  {
    "id": "microsoft-office-web-server",
    "name": "Microsoft Office Web Server",
    "builtwith": true,
    "category": "servers"
  },
  {
    "id": "microsoft-publisher",
    "name": "Microsoft Publisher",
    "wappalyzer": true
  },
  {
    "id": "microsoft-sharepoint",
    "name": "Microsoft SharePoint",
    "wappalyzer": true
  },
  {
    "id": "microsoft-sharepoint-server-2013",
    "name": "Microsoft SharePoint Server 2013",
    "builtwith": true,
    "category": "servers"
  },
  {
    "id": "microsoft-translator",
    "name": "Microsoft Translator",
    "builtwith": true
  },
  {
    "id": "microsoft-word",
    "name": "Microsoft Word",
    "builtwith": true,
    "wappalyzer": true
  },
  {
    "id": "milonic",
    "name": "Milonic",
    "builtwith": true
  },
  {
    "id": "mm-menu",
    "name": "MM Menu",
    "builtwith": true
  },
  {
    "id": "mobile-non-scaleable-content",
    "name": "Mobile Non Scaleable Content",
    "builtwith": true
  },
  {
    "id": "mobile-optimized",
    "name": "Mobile Optimized",
    "builtwith": true
  },
  {
    "id": "mobilecause",
    "name": "MobileCause",
    "builtwith": true
  },
  {
    "id": "mobilemenu",
    "name": "Mobilemenu",
    "builtwith": true
  },
  {
    "id": "mod_ssl",
    "name": "mod_ssl",
    "builtwith": true,
    "category": "security"
  },
  {
    "name": "mod_ssl 2.0.63",
    "builtwith": true,
    "alias": "mod_ssl",
    "category": "security"
  },
  {
    "name": "mod_ssl 2.2.10",
    "builtwith": true,
    "alias": "mod_ssl",
    "category": "security"
  },
  {
    "name": "mod_ssl 2.2.11",
    "builtwith": true,
    "alias": "mod_ssl",
    "category": "security"
  },
  {
    "name": "mod_ssl 2.2.14",
    "builtwith": true,
    "alias": "mod_ssl",
    "category": "security"
  },
  {
    "name": "mod_ssl 2.2.15",
    "builtwith": true,
    "alias": "mod_ssl",
    "category": "security"
  },
  {
    "name": "mod_ssl 2.2.19",
    "builtwith": true,
    "alias": "mod_ssl",
    "category": "security"
  },
  {
    "name": "mod_ssl 2.2.21",
    "builtwith": true,
    "alias": "mod_ssl",
    "category": "security"
  },
  {
    "name": "mod_ssl 2.2.22",
    "builtwith": true,
    "alias": "mod_ssl",
    "category": "security"
  },
  {
    "name": "mod_ssl 2.2.24",
    "builtwith": true,
    "alias": "mod_ssl",
    "category": "security"
  },
  {
    "name": "mod_ssl 2.2.25",
    "builtwith": true,
    "alias": "mod_ssl",
    "category": "security"
  },
  {
    "name": "mod_ssl 2.2.3",
    "builtwith": true,
    "alias": "mod_ssl",
    "category": "security"
  },
  {
    "name": "mod_ssl 2.2.8",
    "builtwith": true,
    "alias": "mod_ssl",
    "category": "security"
  },
  {
    "name": "mod_ssl 2.2.9",
    "builtwith": true,
    "alias": "mod_ssl",
    "category": "security"
  },
  {
    "name": "mod_ssl 2.8.22",
    "builtwith": true,
    "alias": "mod_ssl",
    "category": "security"
  },
  {
    "name": "mod_ssl 2.8.28",
    "builtwith": true,
    "alias": "mod_ssl",
    "category": "security"
  },
  {
    "name": "mod_ssl 2.8.31",
    "builtwith": true,
    "alias": "mod_ssl",
    "category": "security"
  },
  {
    "id": "mod_wsgi",
    "name": "mod_wsgi",
    "builtwith": true,
    "category": "servers"
  },
  {
    "id": "modernizr",
    "name": "Modernizr",
    "builtwith": true,
    "wappalyzer": true,
    "category": "JavaScript library"
  },
  {
    "name": "Modernizr 1.6",
    "builtwith": true,
    "alias": "modernizr",
    "category": "JavaScript library"
  },
  {
    "name": "Modernizr 1.7",
    "builtwith": true,
    "alias": "modernizr",
    "category": "JavaScript library"
  },
  {
    "name": "Modernizr 2.0",
    "builtwith": true,
    "alias": "modernizr",
    "category": "JavaScript library"
  },
  {
    "name": "Modernizr 2.5",
    "builtwith": true,
    "alias": "modernizr",
    "category": "JavaScript library"
  },
  {
    "name": "Modernizr 2.6",
    "builtwith": true,
    "alias": "modernizr",
    "category": "JavaScript library"
  },
  {
    "name": "Modernizr 2.8",
    "builtwith": true,
    "alias": "modernizr",
    "category": "JavaScript library"
  },
  {
    "id": "mollom",
    "name": "Mollom",
    "builtwith": true
  },
  {
    "name": "Moment JS",
    "builtwith": true,
    "alias": "moment-js",
    "category": "JavaScript library"
  },
  {
    "name": "Moment Timezone",
    "wappalyzer": true,
    "alias": "moment-js",
    "category": "JavaScript library"
  },
  {
    "id": "moment-js",
    "name": "Moment.js",
    "wappalyzer": true,
    "category": "JavaScript library"
  },
  {
    "id": "monsido",
    "name": "Monsido",
    "builtwith": true
  },
  {
    "id": "monsterinsights",
    "name": "MonsterInsights",
    "builtwith": true
  },
  {
    "id": "mootools",
    "name": "MooTools",
    "builtwith": true,
    "wappalyzer": true
  },
  {
    "id": "morris-js",
    "name": "morris.js",
    "builtwith": true,
    "category": "JavaScript library"
  },
  {
    "id": "mouse-flow",
    "name": "Mouse Flow",
    "wappalyzer": true
  },
  {
    "id": "mouseflow",
    "name": "Mouseflow",
    "builtwith": true
  },
  {
    "id": "ms-smart-tag-prevention",
    "name": "MS Smart Tag Prevention",
    "builtwith": true
  },
  {
    "id": "msn-bing-webmaster",
    "name": "MSN/Bing Webmaster",
    "builtwith": true
  },
  {
    "id": "mustache",
    "name": "Mustache",
    "builtwith": true,
    "wappalyzer": true
  },
  {
    "id": "myfonts",
    "name": "MyFonts",
    "builtwith": true,
    "category": "fonts"
  },
  {
    "id": "mysql",
    "name": "MySQL",
    "wappalyzer": true
  },
  {
    "id": "mywebsite",
    "name": "MyWebsite",
    "wappalyzer": true
  },
  {
    "id": "ncsa-httpd",
    "name": "NCSA HTTPd",
    "builtwith": true
  },
  {
    "id": "neoncrm",
    "name": "NeonCRM",
    "builtwith": true
  },
  {
    "id": "netlify",
    "name": "Netlify",
    "builtwith": true
  },
  {
    "id": "netobjects-fusion",
    "name": "NetObjects Fusion",
    "builtwith": true
  },
  {
    "id": "netscape-commerce",
    "name": "Netscape Commerce",
    "builtwith": true
  },
  {
    "id": "netscape-enterprise-server",
    "name": "Netscape Enterprise Server",
    "builtwith": true,
    "category": "servers"
  },
  {
    "id": "netscape-fasttrack",
    "name": "Netscape Fasttrack",
    "builtwith": true
  },
  {
    "id": "new-relic",
    "name": "New Relic",
    "builtwith": true,
    "wappalyzer": true
  },
  {
    "id": "nextgen-gallery",
    "name": "NextGEN Gallery",
    "builtwith": true,
    "wappalyzer": true
  },
  {
    "id": "nginx",
    "name": "nginx",
    "builtwith": true,
    "wappalyzer": true,
    "category": "servers"
  },
  {
    "name": "nginx 0.6",
    "builtwith": true,
    "alias": "nginx",
    "category": "servers"
  },
  {
    "name": "nginx 0.7",
    "builtwith": true,
    "alias": "nginx",
    "category": "servers"
  },
  {
    "name": "nginx 1.1",
    "builtwith": true,
    "alias": "nginx",
    "category": "servers"
  },
  {
    "name": "nginx 1.10",
    "builtwith": true,
    "alias": "nginx",
    "category": "servers"
  },
  {
    "name": "Nginx 1.12",
    "builtwith": true,
    "alias": "nginx",
    "category": "servers"
  },
  {
    "name": "Nginx 1.14",
    "builtwith": true,
    "alias": "nginx",
    "category": "servers"
  },
  {
    "name": "Nginx 1.15",
    "builtwith": true,
    "alias": "nginx",
    "category": "servers"
  },
  {
    "name": "Nginx 1.16",
    "builtwith": true,
    "alias": "nginx",
    "category": "servers"
  },
  {
    "name": "Nginx 1.17",
    "builtwith": true,
    "alias": "nginx",
    "category": "servers"
  },
  {
    "name": "nginx 1.4",
    "builtwith": true,
    "alias": "nginx",
    "category": "servers"
  },
  {
    "name": "nginx 1.6",
    "builtwith": true,
    "alias": "nginx",
    "category": "servers"
  },
  {
    "id": "niche-academy",
    "name": "Niche Academy",
    "builtwith": true
  },
  {
    "id": "nifty-corners",
    "name": "Nifty Corners",
    "builtwith": true
  },
  {
    "id": "nivo-slider",
    "name": "Nivo Slider",
    "builtwith": true
  },
  {
    "id": "normalize-css",
    "name": "Normalize CSS",
    "builtwith": true,
    "category": "css"
  },
  {
    "id": "norton-safe-web",
    "name": "Norton Safe Web",
    "builtwith": true
  },
  {
    "id": "nwmatcher",
    "name": "NWMatcher",
    "builtwith": true
  },
  {
    "id": "oembed",
    "name": "oEmbed",
    "builtwith": true
  },
  {
    "id": "omniture-sitecatalyst",
    "name": "Omniture SiteCatalyst",
    "builtwith": true
  },
  {
    "id": "omniupdate",
    "name": "OmniUpdate",
    "builtwith": true
  },
  {
    "id": "onetrust",
    "name": "OneTrust",
    "builtwith": true,
    "wappalyzer": true
  },
  {
    "id": "open-graph-protocol",
    "name": "Open Graph Protocol",
    "builtwith": true
  },
  {
    "id": "openinghoursspecification-schema",
    "name": "OpeningHoursSpecification Schema",
    "builtwith": true
  },
  {
    "id": "opensearch",
    "name": "OpenSearch",
    "builtwith": true
  },
  {
    "id": "openssl",
    "name": "OpenSSL",
    "builtwith": true
  },
  {
    "name": "OpenSSL 0.9.6",
    "builtwith": true,
    "alias": "openssl"
  },
  {
    "name": "OpenSSL 0.9.7",
    "builtwith": true,
    "alias": "openssl"
  },
  {
    "name": "OpenSSL 0.9.8",
    "builtwith": true,
    "alias": "openssl"
  },
  {
    "name": "OpenSSL 1.0.0",
    "builtwith": true,
    "alias": "openssl"
  },
  {
    "name": "OpenSSL 1.0.1",
    "builtwith": true,
    "alias": "openssl"
  },
  {
    "id": "optanon",
    "name": "Optanon",
    "builtwith": true
  },
  {
    "id": "optimizely",
    "name": "Optimizely",
    "builtwith": true,
    "wappalyzer": true
  },
  {
    "id": "oracle-instant-service",
    "name": "Oracle Instant Service",
    "builtwith": true
  },
  {
    "id": "orchard",
    "name": "Orchard",
    "builtwith": true
  },
  {
    "id": "orchard-cms",
    "name": "Orchard CMS",
    "wappalyzer": true
  },
  {
    "id": "organization-schema",
    "name": "Organization Schema",
    "builtwith": true
  },
  {
    "id": "orgsync",
    "name": "OrgSync",
    "builtwith": true
  },
  {
    "id": "osano",
    "name": "Osano",
    "wappalyzer": true
  },
  {
    "id": "oss-cdn",
    "name": "OSS CDN",
    "builtwith": true,
    "category": "cdn"
  },
  {
    "id": "overlib",
    "name": "overLIB",
    "builtwith": true
  },
  {
    "id": "owl-carousel",
    "name": "OWL Carousel",
    "builtwith": true,
    "wappalyzer": true
  },
  {
    "id": "p3p-policy",
    "name": "P3P Policy",
    "builtwith": true
  },
  {
    "id": "pantheon",
    "name": "Pantheon",
    "builtwith": true
  },
  {
    "id": "paperthin-common-spot",
    "name": "Paperthin Common Spot",
    "builtwith": true
  },
  {
    "id": "parallels-plesk-panel",
    "name": "Parallels Plesk Panel",
    "builtwith": true
  },
  {
    "id": "parcel",
    "name": "parcel",
    "wappalyzer": true
  },
  {
    "id": "pardot",
    "name": "Pardot",
    "wappalyzer": true
  },
  {
    "id": "paypal",
    "name": "PayPal",
    "wappalyzer": true
  },
  {
    "id": "percussion",
    "name": "Percussion",
    "wappalyzer": true
  },
  {
    "id": "perl",
    "name": "Perl",
    "builtwith": true,
    "wappalyzer": true
  },
  {
    "id": "person-schema",
    "name": "Person Schema",
    "builtwith": true
  },
  {
    "id": "photoswipe",
    "name": "PhotoSwipe",
    "builtwith": true
  },
  {
    "id": "php",
    "name": "PHP",
    "builtwith": true,
    "wappalyzer": true
  },
  {
    "name": "PHP 7",
    "builtwith": true,
    "alias": "php"
  },
  {
    "id": "php-my-visits",
    "name": "PHP My Visits",
    "builtwith": true
  },
  {
    "name": "phpMyVisites",
    "builtwith": true,
    "alias": "php-my-visits"
  },
  {
    "id": "phusion-passenger",
    "name": "Phusion Passenger",
    "builtwith": true
  },
  {
    "id": "picasa-slideshow",
    "name": "Picasa Slideshow",
    "builtwith": true
  },
  {
    "id": "piclens-lite",
    "name": "Piclens Lite",
    "builtwith": true
  },
  {
    "id": "picosearch",
    "name": "PicoSearch",
    "builtwith": true
  },
  {
    "id": "picture-element",
    "name": "Picture Element",
    "builtwith": true
  },
  {
    "id": "picturefill",
    "name": "Picturefill",
    "builtwith": true
  },
  {
    "id": "pingback-support",
    "name": "Pingback Support",
    "builtwith": true
  },
  {
    "id": "pinterest",
    "name": "Pinterest",
    "builtwith": true,
    "wappalyzer": true
  },
  {
    "id": "pinterest-domain-verify",
    "name": "Pinterest Domain Verify",
    "builtwith": true
  },
  {
    "id": "pixabay",
    "name": "Pixabay",
    "builtwith": true
  },
  {
    "id": "place-schema",
    "name": "Place Schema",
    "builtwith": true
  },
  {
    "id": "placehold-it",
    "name": "Placehold IT",
    "builtwith": true
  },
  {
    "id": "placeholder",
    "name": "Placeholder",
    "builtwith": true
  },
  {
    "id": "platform-for-internet-content-selection",
    "name": "Platform for Internet Content Selection",
    "builtwith": true
  },
  {
    "id": "plone",
    "name": "Plone",
    "builtwith": true,
    "wappalyzer": true
  },
  {
    "id": "png-fix",
    "name": "PNG Fix",
    "builtwith": true
  },
  {
    "id": "polyfill",
    "name": "Polyfill",
    "wappalyzer": true
  },
  {
    "name": "Polyfill IO",
    "builtwith": true,
    "alias": "polyfill"
  },
  {
    "id": "popper",
    "name": "Popper",
    "wappalyzer": true
  },
  {
    "name": "Popper.js",
    "builtwith": true,
    "alias": "popper",
    "category": "JavaScript library"
  },
  {
    "id": "postaladdress-schema",
    "name": "PostalAddress Schema",
    "builtwith": true
  },
  {
    "id": "powerpc",
    "name": "PowerPC",
    "builtwith": true
  },
  {
    "id": "prettyphoto",
    "name": "prettyPhoto",
    "wappalyzer": true
  },
  {
    "id": "prettyprint",
    "name": "PrettyPrint",
    "builtwith": true
  },
  {
    "id": "professionalservice-schema",
    "name": "ProfessionalService Schema",
    "builtwith": true
  },
  {
    "id": "project-seven-popup-menu",
    "name": "Project Seven Popup Menu",
    "builtwith": true
  },
  {
    "id": "proofpoint-url-defense",
    "name": "Proofpoint URL Defense",
    "builtwith": true
  },
  {
    "id": "prototype",
    "name": "Prototype",
    "builtwith": true,
    "wappalyzer": true
  },
  {
    "id": "publitas",
    "name": "Publitas",
    "builtwith": true
  },
  {
    "id": "purl",
    "name": "Purl",
    "builtwith": true
  },
  {
    "id": "python",
    "name": "Python",
    "builtwith": true,
    "wappalyzer": true
  },
  {
    "name": "Python 2.5",
    "builtwith": true,
    "alias": "python"
  },
  {
    "name": "Python 2.6",
    "builtwith": true,
    "alias": "python"
  },
  {
    "name": "Python 2.7",
    "builtwith": true,
    "alias": "python"
  },
  {
    "name": "Python 3.3",
    "builtwith": true,
    "alias": "python"
  },
  {
    "id": "qualaroo",
    "name": "Qualaroo",
    "builtwith": true
  },
  {
    "id": "qualtrics",
    "name": "Qualtrics",
    "builtwith": true
  },
  {
    "name": "Qualtrics Site Intercept",
    "builtwith": true,
    "alias": "qualtrics"
  },
  {
    "id": "quantcast-choice",
    "name": "Quantcast Choice",
    "wappalyzer": true
  },
  {
    "id": "quantcast-measure",
    "name": "Quantcast Measure",
    "wappalyzer": true
  },
  {
    "id": "quantcast-measurement",
    "name": "Quantcast Measurement",
    "builtwith": true
  },
  {
    "id": "raphael",
    "name": "Raphael",
    "wappalyzer": true
  },
  {
    "id": "rasci",
    "name": "RASCi",
    "builtwith": true
  },
  {
    "id": "raven-js",
    "name": "Raven JS",
    "builtwith": true,
    "category": "JavaScript library"
  },
  {
    "id": "rawgit",
    "name": "RawGit",
    "builtwith": true
  },
  {
    "id": "rdf",
    "name": "RDF",
    "builtwith": true
  },
  {
    "id": "reachlocal",
    "name": "ReachLocal",
    "builtwith": true
  },
  {
    "id": "react",
    "name": "React",
    "builtwith": true,
    "wappalyzer": true
  },
  {
    "id": "really-simple-discovery",
    "name": "Really Simple Discovery",
    "builtwith": true
  },
  {
    "id": "recaptcha",
    "name": "reCAPTCHA",
    "builtwith": true,
    "wappalyzer": true
  },
  {
    "name": "reCAPTCHA v2",
    "builtwith": true,
    "alias": "recaptcha"
  },
  {
    "id": "red-hat-enterprise-linux",
    "name": "Red Hat Enterprise Linux",
    "builtwith": true,
    "category": "os"
  },
  {
    "id": "reddit",
    "name": "Reddit",
    "builtwith": true,
    "wappalyzer": true
  },
  {
    "id": "referrer-policy",
    "name": "Referrer Policy",
    "builtwith": true
  },
  {
    "id": "reinvigorate",
    "name": "Reinvigorate",
    "builtwith": true,
    "wappalyzer": true
  },
  {
    "id": "report-uri-csp",
    "name": "Report URI CSP",
    "builtwith": true
  },
  {
    "id": "requirejs",
    "name": "RequireJS",
    "builtwith": true,
    "wappalyzer": true
  },
  {
    "id": "resin",
    "name": "Resin",
    "builtwith": true
  },
  {
    "name": "Resin 3.1",
    "builtwith": true,
    "alias": "resin"
  },
  {
    "id": "respond",
    "name": "Respond",
    "builtwith": true
  },
  {
    "id": "retina-js",
    "name": "Retina JS",
    "builtwith": true,
    "category": "JavaScript library"
  },
  {
    "id": "reveal-js",
    "name": "Reveal.js",
    "wappalyzer": true,
    "category": "JavaScript library"
  },
  {
    "id": "revisit-after",
    "name": "Revisit After",
    "builtwith": true
  },
  {
    "id": "revslider",
    "name": "Revslider",
    "wappalyzer": true
  },
  {
    "id": "roknavmenu",
    "name": "RokNavMenu",
    "builtwith": true
  },
  {
    "id": "royalslider",
    "name": "RoyalSlider",
    "builtwith": true
  },
  {
    "id": "rss",
    "name": "RSS",
    "builtwith": true
  },
  {
    "id": "rtmp-stream",
    "name": "RTMP Stream",
    "builtwith": true
  },
  {
    "id": "ruby",
    "name": "Ruby",
    "wappalyzer": true
  },
  {
    "id": "ruby-on-rails",
    "name": "Ruby on Rails",
    "builtwith": true,
    "wappalyzer": true
  },
  {
    "name": "Ruby on Rails Token",
    "builtwith": true,
    "alias": "ruby-on-rails"
  },
  {
    "id": "ruzeeborders",
    "name": "ruzeeborders",
    "builtwith": true
  },
  {
    "id": "salient",
    "name": "Salient",
    "builtwith": true
  },
  {
    "id": "script-aculo-us",
    "name": "script.aculo.us",
    "builtwith": true,
    "wappalyzer": true
  },
  {
    "id": "select2",
    "name": "Select2",
    "wappalyzer": true
  },
  {
    "id": "selectivizr",
    "name": "selectivizr",
    "builtwith": true
  },
  {
    "id": "semantic-ui",
    "name": "Semantic UI",
    "builtwith": true,
    "wappalyzer": true
  },
  {
    "id": "sentry",
    "name": "Sentry",
    "builtwith": true,
    "wappalyzer": true
  },
  {
    "id": "service-worker",
    "name": "Service Worker",
    "builtwith": true
  },
  {
    "id": "shadowbox",
    "name": "Shadowbox",
    "builtwith": true
  },
  {
    "id": "sharethis",
    "name": "ShareThis",
    "builtwith": true,
    "wappalyzer": true
  },
  {
    "id": "shepherd",
    "name": "Shepherd",
    "builtwith": true
  },
  {
    "name": "Shockwave Flash Embed",
    "builtwith": true,
    "alias": "flash"
  },
  {
    "id": "showclix",
    "name": "ShowClix",
    "builtwith": true
  },
  {
    "id": "shutterstock",
    "name": "Shutterstock",
    "builtwith": true
  },
  {
    "id": "sidr",
    "name": "sidr",
    "builtwith": true
  },
  {
    "id": "sifr",
    "name": "sIFR",
    "builtwith": true,
    "wappalyzer": true
  },
  {
    "id": "signal",
    "name": "Signal",
    "builtwith": true,
    "wappalyzer": true
  },
  {
    "id": "silktide-cookie-consent",
    "name": "Silktide Cookie Consent",
    "builtwith": true
  },
  {
    "id": "silverstripe",
    "name": "SilverStripe",
    "builtwith": true,
    "wappalyzer": true
  },
  {
    "id": "simple-sitemap",
    "name": "Simple Sitemap",
    "builtwith": true
  },
  {
    "id": "simpli-fi",
    "name": "Simpli.fi",
    "builtwith": true
  },
  {
    "id": "sioc",
    "name": "SIOC",
    "builtwith": true
  },
  {
    "id": "site-executive",
    "name": "Site Executive",
    "builtwith": true
  },
  {
    "id": "sitecore",
    "name": "Sitecore",
    "wappalyzer": true
  },
  {
    "id": "sitecore-cms",
    "name": "Sitecore CMS",
    "builtwith": true
  },
  {
    "id": "siteimprove",
    "name": "Siteimprove",
    "builtwith": true
  },
  {
    "id": "sitelinks-search-box",
    "name": "Sitelinks Search Box",
    "builtwith": true
  },
  {
    "id": "sizmek",
    "name": "Sizmek",
    "wappalyzer": true
  },
  {
    "id": "skos",
    "name": "SKOS",
    "builtwith": true
  },
  {
    "id": "skrollr",
    "name": "Skrollr",
    "builtwith": true
  },
  {
    "id": "slick",
    "name": "Slick",
    "wappalyzer": true
  },
  {
    "name": "Slick JS",
    "builtwith": true,
    "alias": "slick"
  },
  {
    "id": "smart-app-banner",
    "name": "Smart App Banner",
    "builtwith": true
  },
  {
    "id": "smartcrawl",
    "name": "SmartCrawl",
    "builtwith": true
  },
  {
    "id": "sothink-html-menu",
    "name": "SoThink HTML Menu",
    "builtwith": true
  },
  {
    "id": "soundmanager2",
    "name": "soundmanager2",
    "builtwith": true
  },
  {
    "id": "specific-media",
    "name": "Specific Media",
    "builtwith": true
  },
  {
    "id": "spectate",
    "name": "Spectate",
    "builtwith": true
  },
  {
    "id": "squarespace",
    "name": "Squarespace",
    "builtwith": true,
    "wappalyzer": true
  },
  {
    "id": "squid",
    "name": "Squid",
    "builtwith": true
  },
  {
    "id": "srcset",
    "name": "srcset",
    "builtwith": true
  },
  {
    "name": "SSL Google Analytics",
    "builtwith": true,
    "alias": "google-analytics"
  },
  {
    "id": "stackpath-bootstrapcdn",
    "name": "StackPath BootstrapCDN",
    "builtwith": true,
    "category": "cdn"
  },
  {
    "id": "statcounter",
    "name": "StatCounter",
    "builtwith": true,
    "wappalyzer": true
  },
  {
    "id": "stellar-js",
    "name": "Stellar.js",
    "builtwith": true,
    "category": "JavaScript library"
  },
  {
    "id": "stream",
    "name": "Stream",
    "builtwith": true
  },
  {
    "id": "strict-transport-security",
    "name": "Strict Transport Security",
    "builtwith": true
  },
  {
    "id": "stripe",
    "name": "Stripe",
    "builtwith": true,
    "wappalyzer": true
  },
  {
    "name": "Stripe v3",
    "builtwith": true,
    "alias": "stripe"
  },
  {
    "id": "stumbleupon",
    "name": "Stumbleupon",
    "builtwith": true
  },
  {
    "id": "style-switcher",
    "name": "Style Switcher",
    "builtwith": true
  },
  {
    "id": "sub-resource-integrity",
    "name": "Sub Resource Integrity",
    "builtwith": true
  },
  {
    "id": "subversion",
    "name": "Subversion",
    "builtwith": true
  },
  {
    "id": "sucuri-cloudproxy",
    "name": "Sucuri Cloudproxy",
    "builtwith": true
  },
  {
    "id": "suhosin",
    "name": "Suhosin",
    "builtwith": true
  },
  {
    "name": "Sun Java System",
    "builtwith": true,
    "alias": "java"
  },
  {
    "id": "sun-one",
    "name": "Sun ONE Web Server",
    "builtwith": true,
    "category": "servers"
  },
  {
    "name": "Sun ONE Web Server v6.1",
    "builtwith": true,
    "alias": "sun-one",
    "category": "servers"
  },
  {
    "id": "superfish-menu",
    "name": "SuperFish Menu",
    "builtwith": true
  },
  {
    "id": "supersized",
    "name": "Supersized",
    "wappalyzer": true
  },
  {
    "id": "survicate",
    "name": "Survicate",
    "builtwith": true
  },
  {
    "id": "swfobject",
    "name": "SWFObject",
    "builtwith": true,
    "wappalyzer": true
  },
  {
    "id": "swipe-js",
    "name": "Swipe JS",
    "builtwith": true,
    "category": "JavaScript library"
  },
  {
    "id": "swiper-slider",
    "name": "Swiper Slider",
    "wappalyzer": true
  },
  {
    "id": "symplicity",
    "name": "Symplicity",
    "builtwith": true
  },
  {
    "id": "tablesorter",
    "name": "Tablesorter",
    "builtwith": true
  },
  {
    "id": "taleo",
    "name": "Taleo",
    "builtwith": true
  },
  {
    "id": "tawk-to",
    "name": "tawk.to",
    "builtwith": true,
    "wappalyzer": true
  },
  {
    "id": "tealium",
    "name": "Tealium",
    "wappalyzer": true
  },
  {
    "id": "telerik-controls",
    "name": "Telerik Controls",
    "builtwith": true
  },
  {
    "id": "texthelp",
    "name": "Texthelp",
    "builtwith": true
  },
  {
    "id": "the-enkoder",
    "name": "The Enkoder",
    "builtwith": true
  },
  {
    "id": "the-seo-framework",
    "name": "The SEO Framework",
    "builtwith": true
  },
  {
    "id": "the-trade-desk",
    "name": "The Trade Desk",
    "builtwith": true
  },
  {
    "id": "the7",
    "name": "The7",
    "builtwith": true
  },
  {
    "id": "themepunch",
    "name": "ThemePunch",
    "builtwith": true
  },
  {
    "id": "thickbox",
    "name": "Thickbox",
    "builtwith": true
  },
  {
    "id": "thing-schema",
    "name": "Thing Schema",
    "builtwith": true
  },
  {
    "id": "ticketswest",
    "name": "TicketsWest",
    "builtwith": true
  },
  {
    "id": "timeago",
    "name": "timeago",
    "builtwith": true
  },
  {
    "id": "tiny-carousel",
    "name": "Tiny Carousel",
    "builtwith": true
  },
  {
    "id": "tinymce",
    "name": "TinyMCE",
    "wappalyzer": true
  },
  {
    "id": "touchswipe",
    "name": "touchSwipe",
    "builtwith": true
  },
  {
    "id": "touristattraction-schema",
    "name": "TouristAttraction Schema",
    "builtwith": true
  },
  {
    "id": "trackjs",
    "name": "TrackJs",
    "wappalyzer": true
  },
  {
    "id": "trafficmarketplace",
    "name": "TrafficMarketplace",
    "builtwith": true
  },
  {
    "id": "trumba",
    "name": "Trumba",
    "builtwith": true
  },
  {
    "id": "turbolinks",
    "name": "TurboLinks",
    "builtwith": true
  },
  {
    "id": "tweenmax",
    "name": "TweenMax",
    "builtwith": true
  },
  {
    "id": "tweet-for-jquery",
    "name": "Tweet for jQuery",
    "builtwith": true
  },
  {
    "id": "twitter",
    "name": "Twitter",
    "wappalyzer": true
  },
  {
    "name": "Twitter Bootstrap",
    "builtwith": true,
    "alias": "bootstrap"
  },
  {
    "id": "twitter-cards",
    "name": "Twitter Cards",
    "builtwith": true
  },
  {
    "id": "twitter-cdn",
    "name": "Twitter CDN",
    "builtwith": true,
    "category": "cdn"
  },
  {
    "id": "twitter-emoji-twemoji",
    "name": "Twitter Emoji (Twemoji)",
    "wappalyzer": true
  },
  {
    "id": "twitter-flight",
    "name": "Twitter Flight",
    "wappalyzer": true
  },
  {
    "id": "twitter-follow-button",
    "name": "Twitter Follow Button",
    "builtwith": true
  },
  {
    "id": "twitter-platform",
    "name": "Twitter Platform",
    "builtwith": true
  },
  {
    "id": "twitter-timeline",
    "name": "Twitter Timeline",
    "builtwith": true
  },
  {
    "id": "twitter-tweet-button",
    "name": "Twitter Tweet Button",
    "builtwith": true
  },
  {
    "id": "twitter-typeahead-js",
    "name": "Twitter typeahead.js",
    "wappalyzer": true,
    "category": "JavaScript library"
  },
  {
    "id": "twitter-widget",
    "name": "Twitter Widget",
    "builtwith": true
  },
  {
    "id": "typeahead-js",
    "name": "Typeahead.js",
    "builtwith": true,
    "category": "JavaScript library"
  },
  {
    "id": "typekit",
    "name": "Typekit",
    "builtwith": true,
    "wappalyzer": true
  },
  {
    "id": "typekit-async",
    "name": "Typekit Async",
    "builtwith": true
  },
  {
    "id": "typo3",
    "name": "TYPO3",
    "builtwith": true
  },
  {
    "name": "TYPO3 CMS",
    "wappalyzer": true,
    "alias": "typo3"
  },
  {
    "id": "typography",
    "name": "Typography",
    "builtwith": true
  },
  {
    "id": "ubercart",
    "name": "Ubercart",
    "builtwith": true
  },
  {
    "id": "ubuntu",
    "name": "Ubuntu",
    "builtwith": true
  },
  {
    "id": "underscore-js",
    "name": "Underscore.js",
    "builtwith": true,
    "wappalyzer": true,
    "category": "JavaScript library"
  },
  {
    "id": "unix",
    "name": "Unix",
    "builtwith": true
  },
  {
    "id": "unpkg",
    "name": "UNPKG",
    "builtwith": true
  },
  {
    "id": "unsemantic",
    "name": "Unsemantic",
    "builtwith": true
  },
  {
    "id": "unsplash",
    "name": "Unsplash",
    "builtwith": true
  },
  {
    "id": "urchin-5",
    "name": "Urchin 5",
    "builtwith": true
  },
  {
    "id": "url-rewriter-net",
    "name": "URL Rewriter .NET",
    "builtwith": true
  },
  {
    "id": "uservoice",
    "name": "UserVoice",
    "wappalyzer": true
  },
  {
    "id": "utf-8",
    "name": "UTF-8",
    "builtwith": true
  },
  {
    "id": "varnish",
    "name": "Varnish",
    "builtwith": true
  },
  {
    "name": "Varnish 5.x",
    "builtwith": true,
    "alias": "varnish"
  },
  {
    "id": "vbscript",
    "name": "VBScript",
    "builtwith": true
  },
  {
    "id": "vcard",
    "name": "vCard",
    "builtwith": true
  },
  {
    "id": "velaro",
    "name": "Velaro",
    "builtwith": true
  },
  {
    "id": "verticalresponse",
    "name": "VerticalResponse",
    "builtwith": true
  },
  {
    "id": "videojs",
    "name": "VideoJS",
    "builtwith": true,
    "wappalyzer": true
  },
  {
    "id": "viewport-meta",
    "name": "Viewport Meta",
    "builtwith": true
  },
  {
    "id": "vimeo",
    "name": "Vimeo",
    "builtwith": true
  },
  {
    "id": "visual-composer-ultimate-addons",
    "name": "Visual Composer Ultimate Addons",
    "builtwith": true
  },
  {
    "id": "visual-studio",
    "name": "Visual Studio",
    "builtwith": true
  },
  {
    "id": "visual-website-optimizer",
    "name": "Visual Website Optimizer",
    "builtwith": true,
    "wappalyzer": true
  },
  {
    "id": "vticker",
    "name": "vTicker",
    "builtwith": true
  },
  {
    "name": "Vue",
    "builtwith": true,
    "alias": "vue-js",
    "category": "JavaScript library"
  },
  {
    "id": "vue-js",
    "name": "Vue.js",
    "wappalyzer": true,
    "category": "JavaScript library"
  },
  {
    "id": "w3-total-cache",
    "name": "W3 Total Cache",
    "builtwith": true,
    "wappalyzer": true
  },
  {
    "id": "wai-aria",
    "name": "WAI-ARIA",
    "builtwith": true
  },
  {
    "id": "web-app-manifest",
    "name": "Web App Manifest",
    "builtwith": true
  },
  {
    "id": "web-site-pro",
    "name": "Web Site Pro",
    "builtwith": true
  },
  {
    "id": "webfont-loader",
    "name": "WebFont Loader",
    "builtwith": true,
    "category": "fonts"
  },
  {
    "id": "webgui",
    "name": "WebGUI",
    "wappalyzer": true
  },
  {
    "id": "webpack",
    "name": "webpack",
    "wappalyzer": true
  },
  {
    "id": "webstar-4d",
    "name": "WebStar 4d",
    "builtwith": true
  },
  {
    "id": "webtrends",
    "name": "WebTrends",
    "builtwith": true,
    "wappalyzer": true
  },
  {
    "id": "webtype",
    "name": "Webtype",
    "builtwith": true
  },
  {
    "id": "win32-header",
    "name": "Win32 Header",
    "builtwith": true
  },
  {
    "id": "windows-8-pinning",
    "name": "Windows 8 Pinning",
    "builtwith": true
  },
  {
    "id": "wistia",
    "name": "Wistia",
    "builtwith": true
  },
  {
    "id": "woopra",
    "name": "Woopra",
    "builtwith": true,
    "wappalyzer": true
  },
  {
    "id": "wordfence",
    "name": "Wordfence",
    "builtwith": true
  },
  {
    "id": "wordpress",
    "name": "WordPress",
    "builtwith": true,
    "wappalyzer": true
  },
  {
    "name": "WordPress 2.5",
    "builtwith": true,
    "alias": "wordpress"
  },
  {
    "name": "WordPress 2.8",
    "builtwith": true,
    "alias": "wordpress"
  },
  {
    "name": "WordPress 3.3",
    "builtwith": true,
    "alias": "wordpress"
  },
  {
    "name": "WordPress 3.5",
    "builtwith": true,
    "alias": "wordpress"
  },
  {
    "name": "WordPress 3.6",
    "builtwith": true,
    "alias": "wordpress"
  },
  {
    "name": "Wordpress 3.9",
    "builtwith": true,
    "alias": "wordpress"
  },
  {
    "name": "WordPress 4.0",
    "builtwith": true,
    "alias": "wordpress"
  },
  {
    "name": "Wordpress 4.1",
    "builtwith": true,
    "alias": "wordpress"
  },
  {
    "name": "Wordpress 4.7",
    "builtwith": true,
    "alias": "wordpress"
  },
  {
    "name": "Wordpress 4.8",
    "builtwith": true,
    "alias": "wordpress"
  },
  {
    "name": "Wordpress 4.9",
    "builtwith": true,
    "alias": "wordpress"
  },
  {
    "name": "Wordpress 5.0",
    "builtwith": true,
    "alias": "wordpress"
  },
  {
    "name": "WordPress 5.2",
    "builtwith": true,
    "alias": "wordpress"
  },
  {
    "name": "WordPress 5.3",
    "builtwith": true,
    "alias": "wordpress"
  },
  {
    "name": "WordPress 5.4",
    "builtwith": true,
    "alias": "wordpress"
  },
  {
    "name": "WordPress 5.5",
    "builtwith": true,
    "alias": "wordpress"
  },
  {
    "name": "WordPress 5.6",
    "builtwith": true,
    "alias": "wordpress"
  },
  {
    "id": "wordpress-grid",
    "name": "WordPress Grid",
    "builtwith": true
  },
  {
    "id": "wordpress-plugins",
    "name": "Wordpress Plugins",
    "builtwith": true
  },
  {
    "id": "wordpress-super-cache",
    "name": "WordPress Super Cache",
    "wappalyzer": true
  },
  {
    "id": "wow",
    "name": "WOW",
    "builtwith": true
  },
  {
    "name": "WOW Slider",
    "builtwith": true,
    "alias": "wow"
  },
  {
    "id": "wp-engine",
    "name": "WP Engine",
    "builtwith": true
  },
  {
    "id": "wp-rocket",
    "name": "WP Rocket",
    "builtwith": true,
    "wappalyzer": true
  },
  {
    "name": "WP Super Cache",
    "builtwith": true,
    "alias": "wordpress-super-cache"
  },
  {
    "id": "wpbakery",
    "name": "WPBakery",
    "builtwith": true
  },
  {
    "id": "wpmu-dev",
    "name": "WPMU DEV",
    "builtwith": true
  },
  {
    "id": "wufoo",
    "name": "Wufoo",
    "builtwith": true
  },
  {
    "id": "wysija",
    "name": "Wysija",
    "builtwith": true
  },
  {
    "id": "x-frame-options",
    "name": "X-Frame-Options",
    "builtwith": true
  },
  {
    "id": "x-ua-compatible",
    "name": "X-UA-Compatible",
    "builtwith": true
  },
  {
    "id": "x-xss-protection",
    "name": "X-XSS-Protection",
    "builtwith": true
  },
  {
    "id": "xhtml-rdf",
    "name": "XHTML RDFa 1.0",
    "builtwith": true
  },
  {
    "id": "xhtml",
    "name": "XHTML Strict",
    "builtwith": true
  },
  {
    "name": "XHTML Transitional",
    "builtwith": true,
    "alias": "xhtml"
  },
  {
    "name": "XHTML Vocabulary",
    "builtwith": true,
    "alias": "xhtml"
  },
  {
    "id": "yahoo-bookmarklet",
    "name": "Yahoo Bookmarklet",
    "builtwith": true
  },
  {
    "id": "yahoo-cdn",
    "name": "Yahoo CDN",
    "builtwith": true,
    "category": "cdn"
  },
  {
    "name": "Yahoo Geocities Analytics",
    "builtwith": true,
    "alias": "yahoo-analytics"
  },
  {
    "id": "yahoo-image-cdn",
    "name": "Yahoo Image CDN",
    "builtwith": true,
    "category": "cdn"
  },
  {
    "id": "yahoo-pipes",
    "name": "Yahoo Pipes",
    "builtwith": true
  },
  {
    "id": "yahoo-site-explorer",
    "name": "Yahoo Site Explorer",
    "builtwith": true
  },
  {
    "id": "yahoo-small-business",
    "name": "Yahoo Small Business",
    "builtwith": true
  },
  {
    "id": "yui",
    "name": "Yahoo User Interface",
    "builtwith": true
  },
  {
    "id": "yahoo-analytics",
    "name": "Yahoo Web Analytics",
    "builtwith": true
  },
  {
    "name": "Yoast Google Analytics for WordPress",
    "builtwith": true,
    "alias": "yahoo-analytics"
  },
  {
    "id": "yoast-plugins",
    "name": "Yoast Plugins",
    "builtwith": true
  },
  {
    "id": "yoast-seo",
    "name": "Yoast SEO",
    "wappalyzer": true
  },
  {
    "id": "yoast-seo-premium",
    "name": "Yoast SEO Premium",
    "builtwith": true
  },
  {
    "id": "yoast-wordpress-seo-plugin",
    "name": "Yoast WordPress SEO Plugin",
    "builtwith": true
  },
  {
    "id": "youtube",
    "name": "YouTube",
    "builtwith": true,
    "wappalyzer": true
  },
  {
    "id": "youtube-iframe-api",
    "name": "YouTube IFrame API",
    "builtwith": true
  },
  {
    "id": "youtube-iframe-upload",
    "name": "YouTube IFrame Upload",
    "builtwith": true
  },
  {
    "id": "youtube-privacy-enchanced",
    "name": "YouTube Privacy Enchanced",
    "builtwith": true
  },
  {
    "id": "youvisit",
    "name": "YouVisit",
    "builtwith": true
  },
  {
    "name": "YUI",
    "wappalyzer": true,
    "alias": "yui"
  },
  {
    "id": "yui-doc",
    "name": "YUI Doc",
    "wappalyzer": true
  },
  {
    "name": "YUI3",
    "builtwith": true,
    "alias": "yui"
  },
  {
    "id": "zencoder-cdn",
    "name": "Zencoder CDN",
    "builtwith": true,
    "category": "cdn"
  },
  {
    "id": "zend-server",
    "name": "Zend Server",
    "builtwith": true,
    "category": "servers"
  },
  {
    "id": "zendesk-chat",
    "name": "Zendesk Chat",
    "wappalyzer": true
  },
  {
    "id": "zeus",
    "name": "Zeus",
    "builtwith": true
  },
  {
    "id": "zoho-salesiq",
    "name": "Zoho SalesIQ",
    "builtwith": true
  },
  {
    "id": "zoom",
    "name": "Zoom",
    "builtwith": true
  },
  {
    "name": "Zoom Video Conferencing",
    "builtwith": true,
    "alias": "zoom"
  },
  {
    "id": "zope",
    "name": "Zope",
    "builtwith": true
  },
  {
    "id": "zopim",
    "name": "Zopim",
    "builtwith": true
  },
  {
    "id": "zserver",
    "name": "ZServer",
    "builtwith": true,
    "category": "servers"
  },
  {
    "id": "zurb-foundation",
    "name": "ZURB Foundation",
    "wappalyzer": true
  }
]